public class TestClass3 {

    private String text = "Hello";
    private String text1 = "World";
    private String text2 = text+text1;
}
******以上为源码/元数据


Classfile /D:/study/collectTest/src/com/company/jvm/test3/TestClass3.class
  Last modified 2021-8-29; size 533 bytes
  MD5 checksum cbb9c0a54eb498fb0e630ea3508cd578
  Compiled from "TestClass3.java"
public class com.company.jvm.test3.TestClass3
  minor version: 0
  major version: 52
  flags: ACC_PUBLIC, ACC_SUPER
Constant pool:
   //超类初始化方法引用
   #1 = Methodref          #12.#23        // java/lang/Object."<init>":()V
   //字符串类型字面量
   #2 = String             #24            // Hello
   //字段的符号引用
   #3 = Fieldref           #11.#25        // com/company/jvm/test3/TestClass3.text:Ljava/lang/String;
   #4 = String             #26            // World
   #5 = Fieldref           #11.#27        // com/company/jvm/test3/TestClass3.text1:Ljava/lang/String;
   //类或接口的符号引用
   #6 = Class              #28            // java/lang/StringBuilder
   //类中方法的符号引用
   #7 = Methodref          #6.#23         // java/lang/StringBuilder."<init>":()V
   #8 = Methodref          #6.#29         // java/lang/StringBuilder.append:(Ljava/lang/String;)Ljava/lang/StringBuilder;
   #9 = Methodref          #6.#30         // java/lang/StringBuilder.toString:()Ljava/lang/String;
  #10 = Fieldref           #11.#31        // com/company/jvm/test3/TestClass3.text2:Ljava/lang/String;
  #11 = Class              #32            // com/company/jvm/test3/TestClass3
  #12 = Class              #33            // java/lang/Object
  #13 = Utf8               text
  #14 = Utf8               Ljava/lang/String;
  #15 = Utf8               text1
  #16 = Utf8               text2
  #17 = Utf8               <init>
  #18 = Utf8               ()V
  #19 = Utf8               Code
  #20 = Utf8               LineNumberTable
  #21 = Utf8               SourceFile
  #22 = Utf8               TestClass3.java
  //字段或方法的符号引用
  #23 = NameAndType        #17:#18        // "<init>":()V
  //UTF-8编码的字符串
  #24 = Utf8               Hello
  #25 = NameAndType        #13:#14        // text:Ljava/lang/String;
  #26 = Utf8               World
  #27 = NameAndType        #15:#14        // text1:Ljava/lang/String;
  #28 = Utf8               java/lang/StringBuilder
  #29 = NameAndType        #34:#35        // append:(Ljava/lang/String;)Ljava/lang/StringBuilder;
  #30 = NameAndType        #36:#37        // toString:()Ljava/lang/String;
  #31 = NameAndType        #16:#14        // text2:Ljava/lang/String;
  #32 = Utf8               com/company/jvm/test3/TestClass3
  #33 = Utf8               java/lang/Object
  #34 = Utf8               append
  #35 = Utf8               (Ljava/lang/String;)Ljava/lang/StringBuilder;
  #36 = Utf8               toString
  #37 = Utf8               ()Ljava/lang/String;
{
  public com.company.jvm.test3.TestClass3();
    descriptor: ()V
    flags: ACC_PUBLIC
    Code:
      stack=3, locals=1, args_size=1
        // 将第0个局部变量的引用类型推送至栈顶
         0: aload_0
         //执行初始化方法
         1: invokespecial #1                  // Method java/lang/Object."<init>":()V
         //
         4: aload_0
         //从常量池将Hello字符串加载至栈顶
         5: ldc           #2                  // String Hello
         //赋值给实例对象的text字段
         7: putfield      #3                  // Field text:Ljava/lang/String;
        10: aload_0
        //从常量池将World字符串加载至栈顶
        11: ldc           #4                  // String World
        //赋值给实例对象的text1字段
        13: putfield      #5                  // Field text1:Ljava/lang/String;
        16: aload_0
        17: new           #6                  // class java/lang/StringBuilder
        20: dup
        21: invokespecial #7                  // Method java/lang/StringBuilder."<init>":()V
        24: aload_0
        25: getfield      #3                  // Field text:Ljava/lang/String;
        28: invokevirtual #8                  // Method java/lang/StringBuilder.append:(Ljava/lang/String;)Ljava/lang/StringBuilder;
        31: aload_0
        32: getfield      #5                  // Field text1:Ljava/lang/String;
        35: invokevirtual #8                  // Method java/lang/StringBuilder.append:(Ljava/lang/String;)Ljava/lang/StringBuilder;
        38: invokevirtual #9                  // Method java/lang/StringBuilder.toString:()Ljava/lang/String;
        41: putfield      #10                 // Field text2:Ljava/lang/String;
        44: return
      LineNumberTable:
        line 8: 0
        line 10: 4
        line 11: 10
        line 12: 16
}
SourceFile: "TestClass3.java"
