public class com.company.jvm.HelloWorldMain
  minor version: 0
  major version: 52
  flags: ACC_PUBLIC, ACC_SUPER
Constant pool:
   #1 = Methodref          #6.#17         // java/lang/Object."<init>":()V
   #2 = Class              #18            // com/company/jvm/HelloWorldMain
   #3 = Methodref          #2.#17         // com/company/jvm/HelloWorldMain."<init>":()V
   #4 = String             #19            // hi
   #5 = Methodref          #2.#20         // com/company/jvm/HelloWorldMain.testMethod:(ILjava/lang/String;)V
   #6 = Class              #21            // java/lang/Object
   #7 = Utf8               <init>
   #8 = Utf8               ()V
   #9 = Utf8               Code
  #10 = Utf8               LineNumberTable
  #11 = Utf8               main
  #12 = Utf8               ([Ljava/lang/String;)V
  #13 = Utf8               testMethod
  #14 = Utf8               (ILjava/lang/String;)V
  #15 = Utf8               SourceFile
  #16 = Utf8               HelloWorldMain.java
  #17 = NameAndType        #7:#8          // "<init>":()V
  #18 = Utf8               com/company/jvm/HelloWorldMain
  #19 = Utf8               hi
  #20 = NameAndType        #13:#14        // testMethod:(ILjava/lang/String;)V
  #21 = Utf8               java/lang/Object
{
  public com.company.jvm.HelloWorldMain();
    descriptor: ()V
    flags: ACC_PUBLIC
    Code:
      stack=1, locals=1, args_size=1
         0: aload_0
         1: invokespecial #1                  // Method java/lang/Object."<init>":()V
         4: return
      LineNumberTable:
        line 8: 0

  public static void main(java.lang.String[]);
    descriptor: ([Ljava/lang/String;)V
    flags: ACC_PUBLIC, ACC_STATIC
    Code:
      stack=3, locals=1, args_size=1
         0: new           #2                  // class com/company/jvm/HelloWorldMain
         3: dup
         4: invokespecial #3                  // Method "<init>":()V
         7: iconst_1
         8: ldc           #4                  // String hi
        10: invokevirtual #5                  // Method testMethod:(ILjava/lang/String;)V
        13: return
      LineNumberTable:
        line 10: 0
        line 11: 13

  public void testMethod(int, java.lang.String);
    descriptor: (ILjava/lang/String;)V
    flags: ACC_PUBLIC
    Code:
      stack=0, locals=3, args_size=3
         0: return
      LineNumberTable:
        line 14: 0
}
SourceFile: "HelloWorldMain.java"
